[{"FortuneRateProtestant":29.999999999999982,"ProfitTaxRateCanton":145,"FortuneRateRoman":40.000000000000036,"CapitalTaxRateChurch":0,"IncomeRateCanton":145,"ProfitTaxRateCity":269.7,"CapitalTaxRateCity":269.7,"FortuneRateCanton":145,"IncomeRateChrist":30.99999999999996,"CapitalTaxRateCanton":145,"FortuneRateChrist":30.99999999999996,"IncomeRateProtestant":29.999999999999982,"IncomeRateCity":229.99999999999997,"IncomeRateRoman":40.000000000000036,"FortuneRateCity":229.99999999999997,"ProfitTaxRateChurch":0,"Location":{"BfsID":1001}},{"FortuneRateProtestant":30.00000000000003,"ProfitTaxRateCanton":145,"FortuneRateRoman":40.000000000000036,"CapitalTaxRateChurch":0,"IncomeRateCanton":145,"ProfitTaxRateCity":249.29,"CapitalTaxRateCity":249.29000000000002,"FortuneRateCanton":145,"IncomeRateChrist":31.000000000000007,"CapitalTaxRateCanton":145,"FortuneRateChrist":31.000000000000007,"IncomeRateProtestant":30.00000000000003,"IncomeRateCity":209.99999999999997,"IncomeRateRoman":40.000000000000036,"FortuneRateCity":209.99999999999997,"ProfitTaxRateChurch":0,"Location":{"BfsID":1002}},{"FortuneRateProtestant":40.000000000000036,"ProfitTaxRateCanton":145,"FortuneRateRoman":40.000000000000036,"CapitalTaxRateChurch":0,"IncomeRateCanton":145,"ProfitTaxRateCity":269.9874,"CapitalTaxRateCity":269.9874,"FortuneRateCanton":145,"IncomeRateChrist":30.99999999999996,"CapitalTaxRateCanton":145,"FortuneRateChrist":30.99999999999996,"IncomeRateProtestant":40.000000000000036,"IncomeRateCity":229.99999999999997,"IncomeRateRoman":40.000000000000036,"FortuneRateCity":229.99999999999997,"ProfitTaxRateChurch":0,"Location":{"BfsID":1004}},{"FortuneRateProtestant":40.000000000000036,"ProfitTaxRateCanton":145,"FortuneRateRoman":41.99999999999999,"CapitalTaxRateChurch":0,"IncomeRateCanton":145,"ProfitTaxRateCity":271.881,"CapitalTaxRateCity":271.881,"FortuneRateCanton":145,"IncomeRateChrist":30.99999999999996,"CapitalTaxRateCanton":145,"FortuneRateChrist":30.99999999999996,"IncomeRateProtestant":40.000000000000036,"IncomeRateCity":229.99999999999997,"IncomeRateRoman":41.99999999999999,"FortuneRateCity":229.99999999999997,"ProfitTaxRateChurch":0,"Location":{"BfsID":1005}},{"FortuneRateProtestant":30.00000000000003,"ProfitTaxRateCanton":145,"FortuneRateRoman":39.99999999999999,"CapitalTaxRateChurch":0,"IncomeRateCanton":145,"ProfitTaxRateCity":259.43500000000006,"CapitalTaxRateCity":259.43500000000006,"FortuneRateCanton":145,"IncomeRateChrist":31.000000000000007,"CapitalTaxRateCanton":145,"FortuneRateChrist":31.000000000000007,"IncomeRateProtestant":30.00000000000003,"IncomeRateCity":220.00000000000003,"IncomeRateRoman":39.99999999999999,"FortuneRateCity":220.00000000000003,"ProfitTaxRateChurch":0,"Location":{"BfsID":1007}},{"FortuneRateProtestant":39.99999999999999,"ProfitTaxRateCanton":145,"FortuneRateRoman":35.00000000000001,"CapitalTaxRateChurch":0,"IncomeRateCanton":145,"ProfitTaxRateCity":255.38980000000004,"CapitalTaxRateCity":255.38980000000004,"FortuneRateCanton":145,"IncomeRateChrist":31.000000000000007,"CapitalTaxRateCanton":145,"FortuneRateChrist":31.000000000000007,"IncomeRateProtestant":39.99999999999999,"IncomeRateCity":220.00000000000003,"IncomeRateRoman":35.00000000000001,"FortuneRateCity":220.00000000000003,"ProfitTaxRateChurch":0,"Location":{"BfsID":1008}},{"FortuneRateProtestant":29.999999999999982,"ProfitTaxRateCanton":145,"FortuneRateRoman":31.000000000000007,"CapitalTaxRateChurch":0,"IncomeRateCanton":145,"ProfitTaxRateCity":245.9182,"CapitalTaxRateCity":245.9182,"FortuneRateCanton":145,"IncomeRateChrist":31.000000000000007,"CapitalTaxRateCanton":145,"FortuneRateChrist":31.000000000000007,"IncomeRateProtestant":29.999999999999982,"IncomeRateCity":215.00000000000003,"IncomeRateRoman":31.000000000000007,"FortuneRateCity":215.00000000000003,"ProfitTaxRateChurch":0,"Location":{"BfsID":1009}},{"FortuneRateProtestant":39.99999999999999,"ProfitTaxRateCanton":145,"FortuneRateRoman":37.999999999999986,"CapitalTaxRateChurch":0,"IncomeRateCanton":145,"ProfitTaxRateCity":238.3625,"CapitalTaxRateCity":238.3625,"FortuneRateCanton":145,"IncomeRateChrist":30.99999999999996,"CapitalTaxRateCanton":145,"FortuneRateChrist":30.99999999999996,"IncomeRateProtestant":39.99999999999999,"IncomeRateCity":200,"IncomeRateRoman":37.999999999999986,"FortuneRateCity":200,"ProfitTaxRateChurch":0,"Location":{"BfsID":1010}},{"FortuneRateProtestant":22.00000000000002,"ProfitTaxRateCanton":145,"FortuneRateRoman":35.00000000000001,"CapitalTaxRateChurch":0,"IncomeRateCanton":145,"ProfitTaxRateCity":212.8329,"CapitalTaxRateCity":212.8329,"FortuneRateCanton":145,"IncomeRateChrist":31.000000000000007,"CapitalTaxRateCanton":145,"FortuneRateChrist":31.000000000000007,"IncomeRateProtestant":22.00000000000002,"IncomeRateCity":180,"IncomeRateRoman":35.00000000000001,"FortuneRateCity":180,"ProfitTaxRateChurch":0,"Location":{"BfsID":1021}},{"FortuneRateProtestant":21.999999999999975,"ProfitTaxRateCanton":145,"FortuneRateRoman":25,"CapitalTaxRateChurch":0,"IncomeRateCanton":145,"ProfitTaxRateCity":174.7621,"CapitalTaxRateCity":174.7621,"FortuneRateCanton":145,"IncomeRateChrist":30.99999999999996,"CapitalTaxRateCanton":145,"FortuneRateChrist":30.99999999999996,"IncomeRateProtestant":21.999999999999975,"IncomeRateCity":150.00000000000003,"IncomeRateRoman":25,"FortuneRateCity":150.00000000000003,"ProfitTaxRateChurch":0,"Location":{"BfsID":1023}},{"FortuneRateProtestant":25,"ProfitTaxRateCanton":145,"FortuneRateRoman":28.49999999999997,"CapitalTaxRateChurch":0,"IncomeRateCanton":145,"ProfitTaxRateCity":243.05575,"CapitalTaxRateCity":243.05575,"FortuneRateCanton":145,"IncomeRateChrist":31.000000000000007,"CapitalTaxRateCanton":145,"FortuneRateChrist":31.000000000000007,"IncomeRateProtestant":25,"IncomeRateCity":215.00000000000003,"IncomeRateRoman":28.49999999999997,"FortuneRateCity":215.00000000000003,"ProfitTaxRateChurch":0,"Location":{"BfsID":1024}},{"FortuneRateProtestant":22.00000000000002,"ProfitTaxRateCanton":145,"FortuneRateRoman":28.000000000000025,"CapitalTaxRateChurch":0,"IncomeRateCanton":145,"ProfitTaxRateCity":212.38920000000002,"CapitalTaxRateCity":212.38920000000002,"FortuneRateCanton":145,"IncomeRateChrist":31.000000000000007,"CapitalTaxRateCanton":145,"FortuneRateChrist":31.000000000000007,"IncomeRateProtestant":22.00000000000002,"IncomeRateCity":185,"IncomeRateRoman":28.000000000000025,"FortuneRateCity":185,"ProfitTaxRateChurch":0,"Location":{"BfsID":1025}},{"FortuneRateProtestant":21.999999999999975,"ProfitTaxRateCanton":145,"FortuneRateRoman":25,"CapitalTaxRateChurch":0,"IncomeRateCanton":145,"ProfitTaxRateCity":164.7414,"CapitalTaxRateCity":164.7414,"FortuneRateCanton":145,"IncomeRateChrist":31.000000000000007,"CapitalTaxRateCanton":145,"FortuneRateChrist":31.000000000000007,"IncomeRateProtestant":21.999999999999975,"IncomeRateCity":140,"IncomeRateRoman":25,"FortuneRateCity":140,"ProfitTaxRateChurch":0,"Location":{"BfsID":1026}},{"FortuneRateProtestant":22.00000000000002,"ProfitTaxRateCanton":145,"FortuneRateRoman":27.99999999999998,"CapitalTaxRateChurch":0,"IncomeRateCanton":145,"ProfitTaxRateCity":207.181,"CapitalTaxRateCity":207.181,"FortuneRateCanton":145,"IncomeRateChrist":31.000000000000007,"CapitalTaxRateCanton":145,"FortuneRateChrist":31.000000000000007,"IncomeRateProtestant":22.00000000000002,"IncomeRateCity":180,"IncomeRateRoman":27.99999999999998,"FortuneRateCity":180,"ProfitTaxRateChurch":0,"Location":{"BfsID":1030}},{"FortuneRateProtestant":21.999999999999975,"ProfitTaxRateCanton":145,"FortuneRateRoman":25.99999999999998,"CapitalTaxRateChurch":0,"IncomeRateCanton":145,"ProfitTaxRateCity":215.5417,"CapitalTaxRateCity":215.5417,"FortuneRateCanton":145,"IncomeRateChrist":31.000000000000007,"CapitalTaxRateCanton":145,"FortuneRateChrist":31.000000000000007,"IncomeRateProtestant":21.999999999999975,"IncomeRateCity":190,"IncomeRateRoman":25.99999999999998,"FortuneRateCity":190,"ProfitTaxRateChurch":0,"Location":{"BfsID":1031}},{"FortuneRateProtestant":22.00000000000002,"ProfitTaxRateCanton":145,"FortuneRateRoman":45.000000000000014,"CapitalTaxRateChurch":0,"IncomeRateCanton":145,"ProfitTaxRateCity":247.75369999999998,"CapitalTaxRateCity":247.75369999999998,"FortuneRateCanton":145,"IncomeRateChrist":31.000000000000007,"CapitalTaxRateCanton":145,"FortuneRateChrist":31.000000000000007,"IncomeRateProtestant":22.00000000000002,"IncomeRateCity":204.99999999999997,"IncomeRateRoman":45.000000000000014,"FortuneRateCity":204.99999999999997,"ProfitTaxRateChurch":0,"Location":{"BfsID":1032}},{"FortuneRateProtestant":22.00000000000002,"ProfitTaxRateCanton":145,"FortuneRateRoman":21.60000000000002,"CapitalTaxRateChurch":0,"IncomeRateCanton":145,"ProfitTaxRateCity":181.67194,"CapitalTaxRateCity":181.67194,"FortuneRateCanton":145,"IncomeRateChrist":31.000000000000007,"CapitalTaxRateCanton":145,"FortuneRateChrist":31.000000000000007,"IncomeRateProtestant":22.00000000000002,"IncomeRateCity":160,"IncomeRateRoman":21.60000000000002,"FortuneRateCity":160,"ProfitTaxRateChurch":0,"Location":{"BfsID":1033}},{"FortuneRateProtestant":22.00000000000002,"ProfitTaxRateCanton":145,"FortuneRateRoman":28.000000000000025,"CapitalTaxRateChurch":0,"IncomeRateCanton":145,"ProfitTaxRateCity":187.4087,"CapitalTaxRateCity":187.4087,"FortuneRateCanton":145,"IncomeRateChrist":31.000000000000007,"CapitalTaxRateCanton":145,"FortuneRateChrist":31.000000000000007,"IncomeRateProtestant":22.00000000000002,"IncomeRateCity":160,"IncomeRateRoman":28.000000000000025,"FortuneRateCity":160,"ProfitTaxRateChurch":0,"Location":{"BfsID":1037}},{"FortuneRateProtestant":21.999999999999975,"ProfitTaxRateCanton":145,"FortuneRateRoman":44.99999999999997,"CapitalTaxRateChurch":0,"IncomeRateCanton":145,"ProfitTaxRateCity":242.976,"CapitalTaxRateCity":242.976,"FortuneRateCanton":145,"IncomeRateChrist":30.99999999999996,"CapitalTaxRateCanton":145,"FortuneRateChrist":30.99999999999996,"IncomeRateProtestant":21.999999999999975,"IncomeRateCity":200,"IncomeRateRoman":44.99999999999997,"FortuneRateCity":200,"ProfitTaxRateChurch":0,"Location":{"BfsID":1039}},{"FortuneRateProtestant":25,"ProfitTaxRateCanton":145,"FortuneRateRoman":25,"CapitalTaxRateChurch":0,"IncomeRateCanton":145,"ProfitTaxRateCity":190.0048,"CapitalTaxRateCity":190.0048,"FortuneRateCanton":145,"IncomeRateChrist":31.000000000000007,"CapitalTaxRateCanton":145,"FortuneRateChrist":31.000000000000007,"IncomeRateProtestant":25,"IncomeRateCity":165,"IncomeRateRoman":25,"FortuneRateCity":165,"ProfitTaxRateChurch":0,"Location":{"BfsID":1040}},{"FortuneRateProtestant":22.00000000000002,"ProfitTaxRateCanton":145,"FortuneRateRoman":42.000000000000036,"CapitalTaxRateChurch":0,"IncomeRateCanton":145,"ProfitTaxRateCity":248.61919999999998,"CapitalTaxRateCity":248.61919999999998,"FortuneRateCanton":145,"IncomeRateChrist":31.000000000000007,"CapitalTaxRateCanton":145,"FortuneRateChrist":31.000000000000007,"IncomeRateProtestant":22.00000000000002,"IncomeRateCity":209.99999999999997,"IncomeRateRoman":42.000000000000036,"FortuneRateCity":209.99999999999997,"ProfitTaxRateChurch":0,"Location":{"BfsID":1041}},{"FortuneRateProtestant":25,"ProfitTaxRateCanton":145,"FortuneRateRoman":22.00000000000002,"CapitalTaxRateChurch":0,"IncomeRateCanton":145,"ProfitTaxRateCity":207.6639,"CapitalTaxRateCity":207.6639,"FortuneRateCanton":145,"IncomeRateChrist":31.000000000000007,"CapitalTaxRateCanton":145,"FortuneRateChrist":31.000000000000007,"IncomeRateProtestant":25,"IncomeRateCity":185,"IncomeRateRoman":22.00000000000002,"FortuneRateCity":185,"ProfitTaxRateChurch":0,"Location":{"BfsID":1051}},{"FortuneRateProtestant":25,"ProfitTaxRateCanton":145,"FortuneRateRoman":25.649999999999995,"CapitalTaxRateChurch":0,"IncomeRateCanton":145,"ProfitTaxRateCity":220.558625,"CapitalTaxRateCity":220.558625,"FortuneRateCanton":145,"IncomeRateChrist":31.000000000000007,"CapitalTaxRateCanton":145,"FortuneRateChrist":31.000000000000007,"IncomeRateProtestant":25,"IncomeRateCity":195,"IncomeRateRoman":25.649999999999995,"FortuneRateCity":195,"ProfitTaxRateChurch":0,"Location":{"BfsID":1052}},{"FortuneRateProtestant":25,"ProfitTaxRateCanton":145,"FortuneRateRoman":20.000000000000018,"CapitalTaxRateChurch":0,"IncomeRateCanton":145,"ProfitTaxRateCity":205.9055,"CapitalTaxRateCity":205.9055,"FortuneRateCanton":145,"IncomeRateChrist":31.000000000000007,"CapitalTaxRateCanton":145,"FortuneRateChrist":31.000000000000007,"IncomeRateProtestant":25,"IncomeRateCity":185,"IncomeRateRoman":20.000000000000018,"FortuneRateCity":185,"ProfitTaxRateChurch":0,"Location":{"BfsID":1053}},{"FortuneRateProtestant":25,"ProfitTaxRateCanton":145,"FortuneRateRoman":25,"CapitalTaxRateChurch":0,"IncomeRateCanton":145,"ProfitTaxRateCity":230.02819999999997,"CapitalTaxRateCity":230.02819999999997,"FortuneRateCanton":145,"IncomeRateChrist":31.000000000000007,"CapitalTaxRateCanton":145,"FortuneRateChrist":31.000000000000007,"IncomeRateProtestant":25,"IncomeRateCity":204.99999999999997,"IncomeRateRoman":25,"FortuneRateCity":204.99999999999997,"ProfitTaxRateChurch":0,"Location":{"BfsID":1054}},{"FortuneRateProtestant":25,"ProfitTaxRateCanton":145,"FortuneRateRoman":20.000000000000018,"CapitalTaxRateChurch":0,"IncomeRateCanton":145,"ProfitTaxRateCity":180.8964,"CapitalTaxRateCity":180.8964,"FortuneRateCanton":145,"IncomeRateChrist":31.000000000000007,"CapitalTaxRateCanton":145,"FortuneRateChrist":31.000000000000007,"IncomeRateProtestant":25,"IncomeRateCity":160,"IncomeRateRoman":20.000000000000018,"FortuneRateCity":160,"ProfitTaxRateChurch":0,"Location":{"BfsID":1055}},{"FortuneRateProtestant":25,"ProfitTaxRateCanton":145,"FortuneRateRoman":35.00000000000001,"CapitalTaxRateChurch":0,"IncomeRateCanton":145,"ProfitTaxRateCity":217.8404,"CapitalTaxRateCity":217.8404,"FortuneRateCanton":145,"IncomeRateChrist":31.000000000000007,"CapitalTaxRateCanton":145,"FortuneRateChrist":31.000000000000007,"IncomeRateProtestant":25,"IncomeRateCity":185,"IncomeRateRoman":35.00000000000001,"FortuneRateCity":185,"ProfitTaxRateChurch":0,"Location":{"BfsID":1056}},{"FortuneRateProtestant":25,"ProfitTaxRateCanton":145,"FortuneRateRoman":25,"CapitalTaxRateChurch":0,"IncomeRateCanton":145,"ProfitTaxRateCity":165.0078,"CapitalTaxRateCity":165.0078,"FortuneRateCanton":145,"IncomeRateChrist":31.000000000000007,"CapitalTaxRateCanton":145,"FortuneRateChrist":31.000000000000007,"IncomeRateProtestant":25,"IncomeRateCity":140,"IncomeRateRoman":25,"FortuneRateCity":140,"ProfitTaxRateChurch":0,"Location":{"BfsID":1058}},{"FortuneRateProtestant":25,"ProfitTaxRateCanton":145,"FortuneRateRoman":25,"CapitalTaxRateChurch":0,"IncomeRateCanton":145,"ProfitTaxRateCity":210.0228,"CapitalTaxRateCity":210.0228,"FortuneRateCanton":145,"IncomeRateChrist":31.000000000000007,"CapitalTaxRateCanton":145,"FortuneRateChrist":31.000000000000007,"IncomeRateProtestant":25,"IncomeRateCity":185,"IncomeRateRoman":25,"FortuneRateCity":185,"ProfitTaxRateChurch":0,"Location":{"BfsID":1059}},{"FortuneRateProtestant":25,"ProfitTaxRateCanton":145,"FortuneRateRoman":23,"CapitalTaxRateChurch":0,"IncomeRateCanton":145,"ProfitTaxRateCity":168.419,"CapitalTaxRateCity":168.419,"FortuneRateCanton":145,"IncomeRateChrist":31.000000000000007,"CapitalTaxRateCanton":145,"FortuneRateChrist":31.000000000000007,"IncomeRateProtestant":25,"IncomeRateCity":145,"IncomeRateRoman":23,"FortuneRateCity":145,"ProfitTaxRateChurch":0,"Location":{"BfsID":1061}},{"FortuneRateProtestant":25,"ProfitTaxRateCanton":145,"FortuneRateRoman":30.00000000000003,"CapitalTaxRateChurch":0,"IncomeRateCanton":145,"ProfitTaxRateCity":224.4518,"CapitalTaxRateCity":224.4518,"FortuneRateCanton":145,"IncomeRateChrist":31.000000000000007,"CapitalTaxRateCanton":145,"FortuneRateChrist":31.000000000000007,"IncomeRateProtestant":25,"IncomeRateCity":195,"IncomeRateRoman":30.00000000000003,"FortuneRateCity":195,"ProfitTaxRateChurch":0,"Location":{"BfsID":1062}},{"FortuneRateProtestant":25,"ProfitTaxRateCanton":145,"FortuneRateRoman":14.449999999999985,"CapitalTaxRateChurch":0,"IncomeRateCanton":145,"ProfitTaxRateCity":106.962185,"CapitalTaxRateCity":106.962185,"FortuneRateCanton":145,"IncomeRateChrist":31.000000000000007,"CapitalTaxRateCanton":145,"FortuneRateChrist":31.000000000000007,"IncomeRateProtestant":25,"IncomeRateCity":90.00000000000001,"IncomeRateRoman":14.449999999999985,"FortuneRateCity":90.00000000000001,"ProfitTaxRateChurch":0,"Location":{"BfsID":1063}},{"FortuneRateProtestant":25,"ProfitTaxRateCanton":145,"FortuneRateRoman":33.00000000000001,"CapitalTaxRateChurch":0,"IncomeRateCanton":145,"ProfitTaxRateCity":201.3066,"CapitalTaxRateCity":201.3066,"FortuneRateCanton":145,"IncomeRateChrist":31.000000000000007,"CapitalTaxRateCanton":145,"FortuneRateChrist":31.000000000000007,"IncomeRateProtestant":25,"IncomeRateCity":170,"IncomeRateRoman":33.00000000000001,"FortuneRateCity":170,"ProfitTaxRateChurch":0,"Location":{"BfsID":1064}},{"FortuneRateProtestant":25,"ProfitTaxRateCanton":145,"FortuneRateRoman":19.99999999999997,"CapitalTaxRateChurch":0,"IncomeRateCanton":145,"ProfitTaxRateCity":170.7176,"CapitalTaxRateCity":170.7176,"FortuneRateCanton":145,"IncomeRateChrist":30.99999999999996,"CapitalTaxRateCanton":145,"FortuneRateChrist":30.99999999999996,"IncomeRateProtestant":25,"IncomeRateCity":150.00000000000003,"IncomeRateRoman":19.99999999999997,"FortuneRateCity":150.00000000000003,"ProfitTaxRateChurch":0,"Location":{"BfsID":1065}},{"FortuneRateProtestant":25,"ProfitTaxRateCanton":145,"FortuneRateRoman":32.00000000000003,"CapitalTaxRateChurch":0,"IncomeRateCanton":145,"ProfitTaxRateCity":241.3699,"CapitalTaxRateCity":241.3699,"FortuneRateCanton":145,"IncomeRateChrist":31.000000000000007,"CapitalTaxRateCanton":145,"FortuneRateChrist":31.000000000000007,"IncomeRateProtestant":25,"IncomeRateCity":209.99999999999997,"IncomeRateRoman":32.00000000000003,"FortuneRateCity":209.99999999999997,"ProfitTaxRateChurch":0,"Location":{"BfsID":1066}},{"FortuneRateProtestant":25,"ProfitTaxRateCanton":145,"FortuneRateRoman":29.999999999999982,"CapitalTaxRateChurch":0,"IncomeRateCanton":145,"ProfitTaxRateCity":209.0345,"CapitalTaxRateCity":209.0345,"FortuneRateCanton":145,"IncomeRateChrist":31.000000000000007,"CapitalTaxRateCanton":145,"FortuneRateChrist":31.000000000000007,"IncomeRateProtestant":25,"IncomeRateCity":180,"IncomeRateRoman":29.999999999999982,"FortuneRateCity":180,"ProfitTaxRateChurch":0,"Location":{"BfsID":1067}},{"FortuneRateProtestant":25,"ProfitTaxRateCanton":145,"FortuneRateRoman":25,"CapitalTaxRateChurch":0,"IncomeRateCanton":145,"ProfitTaxRateCity":165.0144,"CapitalTaxRateCity":165.0144,"FortuneRateCanton":145,"IncomeRateChrist":31.000000000000007,"CapitalTaxRateCanton":145,"FortuneRateChrist":31.000000000000007,"IncomeRateProtestant":25,"IncomeRateCity":140,"IncomeRateRoman":25,"FortuneRateCity":140,"ProfitTaxRateChurch":0,"Location":{"BfsID":1068}},{"FortuneRateProtestant":25,"ProfitTaxRateCanton":145,"FortuneRateRoman":22.00000000000002,"CapitalTaxRateChurch":0,"IncomeRateCanton":145,"ProfitTaxRateCity":152.63569999999999,"CapitalTaxRateCity":152.63569999999999,"FortuneRateCanton":145,"IncomeRateChrist":31.000000000000007,"CapitalTaxRateCanton":145,"FortuneRateChrist":31.000000000000007,"IncomeRateProtestant":25,"IncomeRateCity":130,"IncomeRateRoman":22.00000000000002,"FortuneRateCity":130,"ProfitTaxRateChurch":0,"Location":{"BfsID":1069}},{"FortuneRateProtestant":25,"ProfitTaxRateCanton":145,"FortuneRateRoman":30.00000000000003,"CapitalTaxRateChurch":0,"IncomeRateCanton":145,"ProfitTaxRateCity":214.4746,"CapitalTaxRateCity":214.4746,"FortuneRateCanton":145,"IncomeRateChrist":31.000000000000007,"CapitalTaxRateCanton":145,"FortuneRateChrist":31.000000000000007,"IncomeRateProtestant":25,"IncomeRateCity":185,"IncomeRateRoman":30.00000000000003,"FortuneRateCity":185,"ProfitTaxRateChurch":0,"Location":{"BfsID":1081}},{"FortuneRateProtestant":25,"ProfitTaxRateCanton":145,"FortuneRateRoman":35.00000000000001,"CapitalTaxRateChurch":0,"IncomeRateCanton":145,"ProfitTaxRateCity":223.901,"CapitalTaxRateCity":223.901,"FortuneRateCanton":145,"IncomeRateChrist":31.000000000000007,"CapitalTaxRateCanton":145,"FortuneRateChrist":31.000000000000007,"IncomeRateProtestant":25,"IncomeRateCity":190,"IncomeRateRoman":35.00000000000001,"FortuneRateCity":190,"ProfitTaxRateChurch":0,"Location":{"BfsID":1082}},{"FortuneRateProtestant":25,"ProfitTaxRateCanton":145,"FortuneRateRoman":27.99999999999998,"CapitalTaxRateChurch":0,"IncomeRateCanton":145,"ProfitTaxRateCity":217.745,"CapitalTaxRateCity":217.745,"FortuneRateCanton":145,"IncomeRateChrist":31.000000000000007,"CapitalTaxRateCanton":145,"FortuneRateChrist":31.000000000000007,"IncomeRateProtestant":25,"IncomeRateCity":190,"IncomeRateRoman":27.99999999999998,"FortuneRateCity":190,"ProfitTaxRateChurch":0,"Location":{"BfsID":1083}},{"FortuneRateProtestant":25,"ProfitTaxRateCanton":145,"FortuneRateRoman":20.999999999999996,"CapitalTaxRateChurch":0,"IncomeRateCanton":145,"ProfitTaxRateCity":151.582,"CapitalTaxRateCity":151.582,"FortuneRateCanton":145,"IncomeRateChrist":31.000000000000007,"CapitalTaxRateCanton":145,"FortuneRateChrist":31.000000000000007,"IncomeRateProtestant":25,"IncomeRateCity":130,"IncomeRateRoman":20.999999999999996,"FortuneRateCity":130,"ProfitTaxRateChurch":0,"Location":{"BfsID":1084}},{"FortuneRateProtestant":25,"ProfitTaxRateCanton":145,"FortuneRateRoman":33.00000000000001,"CapitalTaxRateChurch":0,"IncomeRateCanton":145,"ProfitTaxRateCity":236.93239999999997,"CapitalTaxRateCity":236.93239999999997,"FortuneRateCanton":145,"IncomeRateChrist":31.000000000000007,"CapitalTaxRateCanton":145,"FortuneRateChrist":31.000000000000007,"IncomeRateProtestant":25,"IncomeRateCity":204.99999999999997,"IncomeRateRoman":33.00000000000001,"FortuneRateCity":204.99999999999997,"ProfitTaxRateChurch":0,"Location":{"BfsID":1085}},{"FortuneRateProtestant":35.00000000000001,"ProfitTaxRateCanton":145,"FortuneRateRoman":32.500000000000014,"CapitalTaxRateChurch":0,"IncomeRateCanton":145,"ProfitTaxRateCity":217.6771,"CapitalTaxRateCity":217.6771,"FortuneRateCanton":145,"IncomeRateChrist":31.000000000000007,"CapitalTaxRateCanton":145,"FortuneRateChrist":31.000000000000007,"IncomeRateProtestant":35.00000000000001,"IncomeRateCity":185,"IncomeRateRoman":32.500000000000014,"FortuneRateCity":185,"ProfitTaxRateChurch":0,"Location":{"BfsID":1086}},{"FortuneRateProtestant":21.999999999999975,"ProfitTaxRateCanton":145,"FortuneRateRoman":27,"CapitalTaxRateChurch":0,"IncomeRateCanton":145,"ProfitTaxRateCity":176.2965,"CapitalTaxRateCity":176.2965,"FortuneRateCanton":145,"IncomeRateChrist":30.99999999999996,"CapitalTaxRateCanton":145,"FortuneRateChrist":30.99999999999996,"IncomeRateProtestant":21.999999999999975,"IncomeRateCity":150.00000000000003,"IncomeRateRoman":27,"FortuneRateCity":150.00000000000003,"ProfitTaxRateChurch":0,"Location":{"BfsID":1088}},{"FortuneRateProtestant":25,"ProfitTaxRateCanton":145,"FortuneRateRoman":33.00000000000001,"CapitalTaxRateChurch":0,"IncomeRateCanton":145,"ProfitTaxRateCity":256.9418,"CapitalTaxRateCity":256.9418,"FortuneRateCanton":145,"IncomeRateChrist":30.99999999999996,"CapitalTaxRateCanton":145,"FortuneRateChrist":30.99999999999996,"IncomeRateProtestant":25,"IncomeRateCity":225,"IncomeRateRoman":33.00000000000001,"FortuneRateCity":225,"ProfitTaxRateChurch":0,"Location":{"BfsID":1089}},{"FortuneRateProtestant":25,"ProfitTaxRateCanton":145,"FortuneRateRoman":25,"CapitalTaxRateChurch":0,"IncomeRateCanton":145,"ProfitTaxRateCity":235.0186,"CapitalTaxRateCity":235.0186,"FortuneRateCanton":145,"IncomeRateChrist":31.000000000000007,"CapitalTaxRateCanton":145,"FortuneRateChrist":31.000000000000007,"IncomeRateProtestant":25,"IncomeRateCity":209.99999999999997,"IncomeRateRoman":25,"FortuneRateCity":209.99999999999997,"ProfitTaxRateChurch":0,"Location":{"BfsID":1091}},{"FortuneRateProtestant":25,"ProfitTaxRateCanton":145,"FortuneRateRoman":28.000000000000025,"CapitalTaxRateChurch":0,"IncomeRateCanton":145,"ProfitTaxRateCity":212.6247,"CapitalTaxRateCity":212.6247,"FortuneRateCanton":145,"IncomeRateChrist":31.000000000000007,"CapitalTaxRateCanton":145,"FortuneRateChrist":31.000000000000007,"IncomeRateProtestant":25,"IncomeRateCity":185,"IncomeRateRoman":28.000000000000025,"FortuneRateCity":185,"ProfitTaxRateChurch":0,"Location":{"BfsID":1093}},{"FortuneRateProtestant":25,"ProfitTaxRateCanton":145,"FortuneRateRoman":27.500000000000036,"CapitalTaxRateChurch":0,"IncomeRateCanton":145,"ProfitTaxRateCity":212.1661,"CapitalTaxRateCity":212.1661,"FortuneRateCanton":145,"IncomeRateChrist":31.000000000000007,"CapitalTaxRateCanton":145,"FortuneRateChrist":31.000000000000007,"IncomeRateProtestant":25,"IncomeRateCity":185,"IncomeRateRoman":27.500000000000036,"FortuneRateCity":185,"ProfitTaxRateChurch":0,"Location":{"BfsID":1094}},{"FortuneRateProtestant":25,"ProfitTaxRateCanton":145,"FortuneRateRoman":25.99999999999998,"CapitalTaxRateChurch":0,"IncomeRateCanton":145,"ProfitTaxRateCity":190.8794,"CapitalTaxRateCity":190.8794,"FortuneRateCanton":145,"IncomeRateChrist":31.000000000000007,"CapitalTaxRateCanton":145,"FortuneRateChrist":31.000000000000007,"IncomeRateProtestant":25,"IncomeRateCity":165,"IncomeRateRoman":25.99999999999998,"FortuneRateCity":165,"ProfitTaxRateChurch":0,"Location":{"BfsID":1095}},{"FortuneRateProtestant":25,"ProfitTaxRateCanton":145,"FortuneRateRoman":29.999999999999982,"CapitalTaxRateChurch":0,"IncomeRateCanton":145,"ProfitTaxRateCity":179.1909,"CapitalTaxRateCity":179.1909,"FortuneRateCanton":145,"IncomeRateChrist":30.99999999999996,"CapitalTaxRateCanton":145,"FortuneRateChrist":30.99999999999996,"IncomeRateProtestant":25,"IncomeRateCity":150.00000000000003,"IncomeRateRoman":29.999999999999982,"FortuneRateCity":150.00000000000003,"ProfitTaxRateChurch":0,"Location":{"BfsID":1097}},{"FortuneRateProtestant":29.999999999999982,"ProfitTaxRateCanton":145,"FortuneRateRoman":31.999999999999986,"CapitalTaxRateChurch":0,"IncomeRateCanton":145,"ProfitTaxRateCity":231.8693,"CapitalTaxRateCity":231.8693,"FortuneRateCanton":145,"IncomeRateChrist":30.99999999999996,"CapitalTaxRateCanton":145,"FortuneRateChrist":30.99999999999996,"IncomeRateProtestant":29.999999999999982,"IncomeRateCity":200,"IncomeRateRoman":31.999999999999986,"FortuneRateCity":200,"ProfitTaxRateChurch":0,"Location":{"BfsID":1098}},{"FortuneRateProtestant":25,"ProfitTaxRateCanton":145,"FortuneRateRoman":25,"CapitalTaxRateChurch":0,"IncomeRateCanton":145,"ProfitTaxRateCity":150.006,"CapitalTaxRateCity":150.006,"FortuneRateCanton":145,"IncomeRateChrist":30.99999999999996,"CapitalTaxRateCanton":145,"FortuneRateChrist":30.99999999999996,"IncomeRateProtestant":25,"IncomeRateCity":125.00000000000003,"IncomeRateRoman":25,"FortuneRateCity":125.00000000000003,"ProfitTaxRateChurch":0,"Location":{"BfsID":1099}},{"FortuneRateProtestant":25,"ProfitTaxRateCanton":145,"FortuneRateRoman":35.00000000000001,"CapitalTaxRateChurch":0,"IncomeRateCanton":145,"ProfitTaxRateCity":213.881,"CapitalTaxRateCity":213.881,"FortuneRateCanton":145,"IncomeRateChrist":31.000000000000007,"CapitalTaxRateCanton":145,"FortuneRateChrist":31.000000000000007,"IncomeRateProtestant":25,"IncomeRateCity":180,"IncomeRateRoman":35.00000000000001,"FortuneRateCity":180,"ProfitTaxRateChurch":0,"Location":{"BfsID":1100}},{"FortuneRateProtestant":25,"ProfitTaxRateCanton":145,"FortuneRateRoman":21.999999999999975,"CapitalTaxRateChurch":0,"IncomeRateCanton":145,"ProfitTaxRateCity":187.4296,"CapitalTaxRateCity":187.4296,"FortuneRateCanton":145,"IncomeRateChrist":31.000000000000007,"CapitalTaxRateCanton":145,"FortuneRateChrist":31.000000000000007,"IncomeRateProtestant":25,"IncomeRateCity":165,"IncomeRateRoman":21.999999999999975,"FortuneRateCity":165,"ProfitTaxRateChurch":0,"Location":{"BfsID":1102}},{"FortuneRateProtestant":25,"ProfitTaxRateCanton":145,"FortuneRateRoman":25,"CapitalTaxRateChurch":0,"IncomeRateCanton":145,"ProfitTaxRateCity":210.015,"CapitalTaxRateCity":210.015,"FortuneRateCanton":145,"IncomeRateChrist":31.000000000000007,"CapitalTaxRateCanton":145,"FortuneRateChrist":31.000000000000007,"IncomeRateProtestant":25,"IncomeRateCity":185,"IncomeRateRoman":25,"FortuneRateCity":185,"ProfitTaxRateChurch":0,"Location":{"BfsID":1103}},{"FortuneRateProtestant":25,"ProfitTaxRateCanton":145,"FortuneRateRoman":25.500000000000036,"CapitalTaxRateChurch":0,"IncomeRateCanton":145,"ProfitTaxRateCity":235.44490000000002,"CapitalTaxRateCity":235.44490000000002,"FortuneRateCanton":145,"IncomeRateChrist":31.000000000000007,"CapitalTaxRateCanton":145,"FortuneRateChrist":31.000000000000007,"IncomeRateProtestant":25,"IncomeRateCity":209.99999999999997,"IncomeRateRoman":25.500000000000036,"FortuneRateCity":209.99999999999997,"ProfitTaxRateChurch":0,"Location":{"BfsID":1104}},{"FortuneRateProtestant":29.999999999999982,"ProfitTaxRateCanton":145,"FortuneRateRoman":30.99999999999996,"CapitalTaxRateChurch":0,"IncomeRateCanton":145,"ProfitTaxRateCity":260.89,"CapitalTaxRateCity":260.89,"FortuneRateCanton":145,"IncomeRateChrist":30.99999999999996,"CapitalTaxRateCanton":145,"FortuneRateChrist":30.99999999999996,"IncomeRateProtestant":29.999999999999982,"IncomeRateCity":229.99999999999997,"IncomeRateRoman":30.99999999999996,"FortuneRateCity":229.99999999999997,"ProfitTaxRateChurch":0,"Location":{"BfsID":1107}},{"FortuneRateProtestant":35.00000000000001,"ProfitTaxRateCanton":145,"FortuneRateRoman":29.000000000000004,"CapitalTaxRateChurch":0,"IncomeRateCanton":145,"ProfitTaxRateCity":244.7428,"CapitalTaxRateCity":244.7428,"FortuneRateCanton":145,"IncomeRateChrist":31.000000000000007,"CapitalTaxRateCanton":145,"FortuneRateChrist":31.000000000000007,"IncomeRateProtestant":35.00000000000001,"IncomeRateCity":215.00000000000003,"IncomeRateRoman":29.000000000000004,"FortuneRateCity":215.00000000000003,"ProfitTaxRateChurch":0,"Location":{"BfsID":1121}},{"FortuneRateProtestant":26.499999999999968,"ProfitTaxRateCanton":145,"FortuneRateRoman":41.000000000000014,"CapitalTaxRateChurch":0,"IncomeRateCanton":145,"ProfitTaxRateCity":268.30044999999996,"CapitalTaxRateCity":268.30044999999996,"FortuneRateCanton":145,"IncomeRateChrist":30.99999999999996,"CapitalTaxRateCanton":145,"FortuneRateChrist":30.99999999999996,"IncomeRateProtestant":26.499999999999968,"IncomeRateCity":229.99999999999997,"IncomeRateRoman":41.000000000000014,"FortuneRateCity":229.99999999999997,"ProfitTaxRateChurch":0,"Location":{"BfsID":1122}},{"FortuneRateProtestant":26.500000000000014,"ProfitTaxRateCanton":145,"FortuneRateRoman":28.000000000000025,"CapitalTaxRateChurch":0,"IncomeRateCanton":145,"ProfitTaxRateCity":212.8794,"CapitalTaxRateCity":212.8794,"FortuneRateCanton":145,"IncomeRateChrist":31.000000000000007,"CapitalTaxRateCanton":145,"FortuneRateChrist":31.000000000000007,"IncomeRateProtestant":26.500000000000014,"IncomeRateCity":185,"IncomeRateRoman":28.000000000000025,"FortuneRateCity":185,"ProfitTaxRateChurch":0,"Location":{"BfsID":1123}},{"FortuneRateProtestant":26.500000000000014,"ProfitTaxRateCanton":145,"FortuneRateRoman":28.000000000000025,"CapitalTaxRateChurch":0,"IncomeRateCanton":145,"ProfitTaxRateCity":197.8476,"CapitalTaxRateCity":197.8476,"FortuneRateCanton":145,"IncomeRateChrist":31.000000000000007,"CapitalTaxRateCanton":145,"FortuneRateChrist":31.000000000000007,"IncomeRateProtestant":26.500000000000014,"IncomeRateCity":170,"IncomeRateRoman":28.000000000000025,"FortuneRateCity":170,"ProfitTaxRateChurch":0,"Location":{"BfsID":1125}},{"FortuneRateProtestant":25,"ProfitTaxRateCanton":145,"FortuneRateRoman":29.000000000000004,"CapitalTaxRateChurch":0,"IncomeRateCanton":145,"ProfitTaxRateCity":228.5806,"CapitalTaxRateCity":228.5806,"FortuneRateCanton":145,"IncomeRateChrist":30.99999999999996,"CapitalTaxRateCanton":145,"FortuneRateChrist":30.99999999999996,"IncomeRateProtestant":25,"IncomeRateCity":200,"IncomeRateRoman":29.000000000000004,"FortuneRateCity":200,"ProfitTaxRateChurch":0,"Location":{"BfsID":1127}},{"FortuneRateProtestant":35.00000000000001,"ProfitTaxRateCanton":145,"FortuneRateRoman":29.000000000000004,"CapitalTaxRateChurch":0,"IncomeRateCanton":145,"ProfitTaxRateCity":244.4962,"CapitalTaxRateCity":244.4962,"FortuneRateCanton":145,"IncomeRateChrist":31.000000000000007,"CapitalTaxRateCanton":145,"FortuneRateChrist":31.000000000000007,"IncomeRateProtestant":35.00000000000001,"IncomeRateCity":215.00000000000003,"IncomeRateRoman":29.000000000000004,"FortuneRateCity":215.00000000000003,"ProfitTaxRateChurch":0,"Location":{"BfsID":1128}},{"FortuneRateProtestant":35.00000000000001,"ProfitTaxRateCanton":145,"FortuneRateRoman":41.000000000000014,"CapitalTaxRateChurch":0,"IncomeRateCanton":145,"ProfitTaxRateCity":249.8096,"CapitalTaxRateCity":249.8096,"FortuneRateCanton":145,"IncomeRateChrist":31.000000000000007,"CapitalTaxRateCanton":145,"FortuneRateChrist":31.000000000000007,"IncomeRateProtestant":35.00000000000001,"IncomeRateCity":209.99999999999997,"IncomeRateRoman":41.000000000000014,"FortuneRateCity":209.99999999999997,"ProfitTaxRateChurch":0,"Location":{"BfsID":1129}},{"FortuneRateProtestant":26.499999999999968,"ProfitTaxRateCanton":145,"FortuneRateRoman":41.000000000000014,"CapitalTaxRateChurch":0,"IncomeRateCanton":145,"ProfitTaxRateCity":268.74275,"CapitalTaxRateCity":268.74275,"FortuneRateCanton":145,"IncomeRateChrist":30.99999999999996,"CapitalTaxRateCanton":145,"FortuneRateChrist":30.99999999999996,"IncomeRateProtestant":26.499999999999968,"IncomeRateCity":229.99999999999997,"IncomeRateRoman":41.000000000000014,"FortuneRateCity":229.99999999999997,"ProfitTaxRateChurch":0,"Location":{"BfsID":1131}},{"FortuneRateProtestant":34.999999999999964,"ProfitTaxRateCanton":145,"FortuneRateRoman":44.99999999999997,"CapitalTaxRateChurch":0,"IncomeRateCanton":145,"ProfitTaxRateCity":244.2296,"CapitalTaxRateCity":244.2296,"FortuneRateCanton":145,"IncomeRateChrist":30.99999999999996,"CapitalTaxRateCanton":145,"FortuneRateChrist":30.99999999999996,"IncomeRateProtestant":34.999999999999964,"IncomeRateCity":200,"IncomeRateRoman":44.99999999999997,"FortuneRateCity":200,"ProfitTaxRateChurch":0,"Location":{"BfsID":1132}},{"FortuneRateProtestant":35.00000000000001,"ProfitTaxRateCanton":145,"FortuneRateRoman":44.99999999999997,"CapitalTaxRateChurch":0,"IncomeRateCanton":145,"ProfitTaxRateCity":283.9194,"CapitalTaxRateCity":283.9194,"FortuneRateCanton":145,"IncomeRateChrist":31.000000000000007,"CapitalTaxRateCanton":145,"FortuneRateChrist":31.000000000000007,"IncomeRateProtestant":35.00000000000001,"IncomeRateCity":240.00000000000003,"IncomeRateRoman":44.99999999999997,"FortuneRateCity":240.00000000000003,"ProfitTaxRateChurch":0,"Location":{"BfsID":1135}},{"FortuneRateProtestant":30.00000000000003,"ProfitTaxRateCanton":145,"FortuneRateRoman":39.99999999999999,"CapitalTaxRateChurch":0,"IncomeRateCanton":145,"ProfitTaxRateCity":233.92610000000002,"CapitalTaxRateCity":233.92610000000002,"FortuneRateCanton":145,"IncomeRateChrist":31.000000000000007,"CapitalTaxRateCanton":145,"FortuneRateChrist":31.000000000000007,"IncomeRateProtestant":30.00000000000003,"IncomeRateCity":195,"IncomeRateRoman":39.99999999999999,"FortuneRateCity":195,"ProfitTaxRateChurch":0,"Location":{"BfsID":1136}},{"FortuneRateProtestant":26.500000000000014,"ProfitTaxRateCanton":145,"FortuneRateRoman":27.99999999999998,"CapitalTaxRateChurch":0,"IncomeRateCanton":145,"ProfitTaxRateCity":207.86635,"CapitalTaxRateCity":207.86635,"FortuneRateCanton":145,"IncomeRateChrist":31.000000000000007,"CapitalTaxRateCanton":145,"FortuneRateChrist":31.000000000000007,"IncomeRateProtestant":26.500000000000014,"IncomeRateCity":180,"IncomeRateRoman":27.99999999999998,"FortuneRateCity":180,"ProfitTaxRateChurch":0,"Location":{"BfsID":1137}},{"FortuneRateProtestant":26.499999999999968,"ProfitTaxRateCanton":145,"FortuneRateRoman":40.000000000000036,"CapitalTaxRateChurch":0,"IncomeRateCanton":145,"ProfitTaxRateCity":266.81624999999997,"CapitalTaxRateCity":266.81624999999997,"FortuneRateCanton":145,"IncomeRateChrist":30.99999999999996,"CapitalTaxRateCanton":145,"FortuneRateChrist":30.99999999999996,"IncomeRateProtestant":26.499999999999968,"IncomeRateCity":229.99999999999997,"IncomeRateRoman":40.000000000000036,"FortuneRateCity":229.99999999999997,"ProfitTaxRateChurch":0,"Location":{"BfsID":1139}},{"FortuneRateProtestant":26.500000000000014,"ProfitTaxRateCanton":145,"FortuneRateRoman":32.00000000000003,"CapitalTaxRateChurch":0,"IncomeRateCanton":145,"ProfitTaxRateCity":250.86525000000003,"CapitalTaxRateCity":250.86525000000003,"FortuneRateCanton":145,"IncomeRateChrist":31.000000000000007,"CapitalTaxRateCanton":145,"FortuneRateChrist":31.000000000000007,"IncomeRateProtestant":26.500000000000014,"IncomeRateCity":220.00000000000003,"IncomeRateRoman":32.00000000000003,"FortuneRateCity":220.00000000000003,"ProfitTaxRateChurch":0,"Location":{"BfsID":1140}},{"FortuneRateProtestant":26.500000000000014,"ProfitTaxRateCanton":145,"FortuneRateRoman":40.000000000000036,"CapitalTaxRateChurch":0,"IncomeRateCanton":145,"ProfitTaxRateCity":248.1721,"CapitalTaxRateCity":248.1721,"FortuneRateCanton":145,"IncomeRateChrist":31.000000000000007,"CapitalTaxRateCanton":145,"FortuneRateChrist":31.000000000000007,"IncomeRateProtestant":26.500000000000014,"IncomeRateCity":209.99999999999997,"IncomeRateRoman":40.000000000000036,"FortuneRateCity":209.99999999999997,"ProfitTaxRateChurch":0,"Location":{"BfsID":1142}},{"FortuneRateProtestant":26.500000000000014,"ProfitTaxRateCanton":145,"FortuneRateRoman":26.00000000000002,"CapitalTaxRateChurch":0,"IncomeRateCanton":145,"ProfitTaxRateCity":236.048,"CapitalTaxRateCity":236.048,"FortuneRateCanton":145,"IncomeRateChrist":31.000000000000007,"CapitalTaxRateCanton":145,"FortuneRateChrist":31.000000000000007,"IncomeRateProtestant":26.500000000000014,"IncomeRateCity":209.99999999999997,"IncomeRateRoman":26.00000000000002,"FortuneRateCity":209.99999999999997,"ProfitTaxRateChurch":0,"Location":{"BfsID":1143}},{"FortuneRateProtestant":35.00000000000001,"ProfitTaxRateCanton":145,"FortuneRateRoman":44.99999999999997,"CapitalTaxRateChurch":0,"IncomeRateCanton":145,"ProfitTaxRateCity":262.17900000000003,"CapitalTaxRateCity":262.17900000000003,"FortuneRateCanton":145,"IncomeRateChrist":31.000000000000007,"CapitalTaxRateCanton":145,"FortuneRateChrist":31.000000000000007,"IncomeRateProtestant":35.00000000000001,"IncomeRateCity":220.00000000000003,"IncomeRateRoman":44.99999999999997,"FortuneRateCity":220.00000000000003,"ProfitTaxRateChurch":0,"Location":{"BfsID":1145}},{"FortuneRateProtestant":25,"ProfitTaxRateCanton":145,"FortuneRateRoman":29.000000000000004,"CapitalTaxRateChurch":0,"IncomeRateCanton":145,"ProfitTaxRateCity":233.60139999999996,"CapitalTaxRateCity":233.60139999999996,"FortuneRateCanton":145,"IncomeRateChrist":31.000000000000007,"CapitalTaxRateCanton":145,"FortuneRateChrist":31.000000000000007,"IncomeRateProtestant":25,"IncomeRateCity":204.99999999999997,"IncomeRateRoman":29.000000000000004,"FortuneRateCity":204.99999999999997,"ProfitTaxRateChurch":0,"Location":{"BfsID":1146}},{"FortuneRateProtestant":26.500000000000014,"ProfitTaxRateCanton":145,"FortuneRateRoman":32.00000000000003,"CapitalTaxRateChurch":0,"IncomeRateCanton":145,"ProfitTaxRateCity":249.86865000000003,"CapitalTaxRateCity":249.86865000000003,"FortuneRateCanton":145,"IncomeRateChrist":31.000000000000007,"CapitalTaxRateCanton":145,"FortuneRateChrist":31.000000000000007,"IncomeRateProtestant":26.500000000000014,"IncomeRateCity":220.00000000000003,"IncomeRateRoman":32.00000000000003,"FortuneRateCity":220.00000000000003,"ProfitTaxRateChurch":0,"Location":{"BfsID":1147}},{"FortuneRateProtestant":35.00000000000001,"ProfitTaxRateCanton":145,"FortuneRateRoman":35.999999999999986,"CapitalTaxRateChurch":0,"IncomeRateCanton":145,"ProfitTaxRateCity":225.8275,"CapitalTaxRateCity":225.8275,"FortuneRateCanton":145,"IncomeRateChrist":31.000000000000007,"CapitalTaxRateCanton":145,"FortuneRateChrist":31.000000000000007,"IncomeRateProtestant":35.00000000000001,"IncomeRateCity":190,"IncomeRateRoman":35.999999999999986,"FortuneRateCity":190,"ProfitTaxRateChurch":0,"Location":{"BfsID":1150}},{"FortuneRateProtestant":35,"ProfitTaxRateCanton":145,"FortuneRateRoman":33,"CapitalTaxRateChurch":0,"IncomeRateCanton":145,"ProfitTaxRateCity":243.192,"CapitalTaxRateCity":243.192,"FortuneRateCanton":145,"IncomeRateChrist":31.000000000000007,"CapitalTaxRateCanton":145,"FortuneRateChrist":31,"IncomeRateProtestant":35.00000000000001,"IncomeRateCity":209.99999999999997,"IncomeRateRoman":33.00000000000001,"FortuneRateCity":209.99999999999997,"ProfitTaxRateChurch":0,"Location":{"BfsID":1151}}]